d6tflow/__init__.py
d6tflow/cache.py
d6tflow/functional.py
d6tflow/pipes.py
d6tflow/settings.py
d6tflow/utils.py
d6tflow/targets/__init__.py
d6tflow/targets/dt.py
d6tflow/targets/h5.py
d6tflow/targets/tf.py
d6tflow/targets/torch.py
d6tflow/tasks/__init__.py
d6tflow/tasks/dt.py
d6tflow/tasks/h5.py
d6tflow/tasks/tf.py
d6tflow/tasks/torch.py
d6tflow-0.2.8.dist-info/LICENSE
d6tflow-0.2.8.dist-info/METADATA
d6tflow-0.2.8.dist-info/WHEEL
d6tflow-0.2.8.dist-info/top_level.txt
d6tflow-0.2.8.dist-info/RECORD
